{
    "data":[
        [
            {
                "dn" : "OU=OPS",
                "name" : "OPS"
            }
        ],
        [
            "_comment: Start point of 30516 OU",
            {
                "dn" : "OU=30516,OU=OPS",
                "name" : "30516"
            }
        ],
        [
            "_comment: Start point of 30618 OU",
            {
                "dn" : "OU=30618,OU=OPS",
                "name" : "30618"
            }
        ],
        [
            "_comment: Start point of ACO OU",
            {
                "dn" : "OU=ACO,OU=OPS",
                "name" : "ACO"
            },
            {
                "dn" : "OU=none,OU=ACO,OU=OPS",
                "name" : "none"
            },
            {
                "dn" : "OU=nonoe,OU=ACO,OU=OPS",
                "name" : "nonoe"
            },
            {
                "dn" : "OU=organization mail,OU=ACO,OU=OPS",
                "name" : "organization mail"
            }
        ],
        [
            "_comment: Start point of AUDIT OU",
            {
                "dn" : "OU=AUDIT,OU=OPS",
                "name" : "AUDIT"
            },
            {
                "dn" : "OU=disable,OU=AUDIT,OU=OPS",
                "name" : "disable"
            },
            {
                "dn" : "OU=none,OU=AUDIT,OU=OPS",
                "name" : "none"
            }
        ],
        [
            "_comment: Start point of CEO OU",
            {
                "dn" : "OU=CEO,OU=OPS",
                "name" : "CEO"
            },
            {
                "dn" : "OU=disable,OU=CEO,OU=OPS",
                "name" : "disable"
            }
        ],
        [
            "_comment: Start point of Connect OU",
            {
                "dn" : "OU=Connect,OU=OPS",
                "name" : "Connect"
            }
        ],
        [
            "_comment: Start point of Default OU",
            {
                "dn" : "OU=Default,OU=OPS",
                "name" : "Default"
            },
            {
                "dn" : "OU=Hospital,OU=Default,OU=OPS",
                "name" : "Hospital"
            }
        ],
        [
            "_comment: Start point of FINANCE OU",
            {
                "dn" : "OU=FINANCE,OU=OPS",
                "name" : "FINANCE"
            },
            {
                "dn" : "OU=disable,OU=FINANCE,OU=OPS",
                "name" : "disable"
            },
            {
                "dn" : "OU=employee,OU=FINANCE,OU=OPS",
                "name" : "employee"
            },
            {
                "dn" : "OU=none,OU=FINANCE,OU=OPS",
                "name" : "none"
            },
            {
                "dn" : "OU=organization mail,OU=FINANCE,OU=OPS",
                "name" : "organization mail"
            },
            {
                "dn" : "OU=transfer,OU=FINANCE,OU=OPS",
                "name" : "transfer"
            }
        ],
        [
            "_comment: Start point of GNAD OU",
            {
                "dn" : "OU=GNAD,OU=OPS",
                "name" : "GNAD"
            },
            {
                "dn" : "OU=disable,OU=GNAD,OU=OPS",
                "name" : "disable"
            },
            {
                "dn" : "OU=employee,OU=GNAD,OU=OPS",
                "name" : "employee"
            },
            {
                "dn" : "OU=none,OU=GNAD,OU=OPS",
                "name" : "none"
            },
            {
                "dn" : "OU=organization mail,OU=GNAD,OU=OPS",
                "name" : "organization mail"
            },
            {
                "dn" : "OU=user กลางเข้าเครื่อง,OU=GNAD,OU=OPS",
                "name" : "user กลางเข้าเครื่อง"
            }
        ],
        [
            "_comment: Start point of ICTC OU",
            {
                "dn" : "OU=ICTC,OU=OPS",
                "name" : "ICTC"
            },
            {
                "dn" : "OU=admin,OU=ICTC,OU=OPS",
                "name" : "admin"
            },
            {
                "dn" : "OU=data trade,OU=ICTC,OU=OPS",
                "name" : "data trade"
            },
            {
                "dn" : "OU=developer,OU=ICTC,OU=OPS",
                "name" : "developer"
            },
            {
                "dn" : "OU=director,OU=ICTC,OU=OPS",
                "name" : "director"
            },
            {
                "dn" : "OU=disable,OU=ICTC,OU=OPS",
                "name" : "disable"
            },
            {
                "dn" : "OU=ePayment,OU=ICTC,OU=OPS",
                "name" : "ePayment"
            },
            {
                "dn" : "OU=ICTCTest,OU=ICTC,OU=OPS",
                "name" : "ICTCTest"
            },
            {
                "dn" : "OU=innovation,OU=ICTC,OU=OPS",
                "name" : "innovation"
            },
            {
                "dn" : "OU=MOC Event Big Data,OU=ICTC,OU=OPS",
                "name" : "MOC Event Big Data"
            },
            {
                "dn" : "OU=network,OU=ICTC,OU=OPS",
                "name" : "network"
            },
            {
                "dn" : "OU=organization mail,OU=ICTC,OU=OPS",
                "name" : "organization mail"
            },
            {
                "dn" : "OU=planning,OU=ICTC,OU=OPS",
                "name" : "planning"
            }
        ],
        [
            "_comment: Start point of INSPEC OU",
            {
                "dn" : "OU=INSPEC,OU=OPS",
                "name" : "INSPEC"
            },
            {
                "dn" : "OU=none,OU=INSPEC,OU=OPS",
                "name" : "none"
            },
            {
                "dn" : "OU=organization mail,OU=INSPEC,OU=OPS",
                "name" : "organization mail"
            }
        ],
        [
            "_comment: Start point of KBP OU",
            {
                "dn" : "OU=KBP,OU=OPS",
                "name" : "KBP"
            },
            {
                "dn" : "OU=disable,OU=KBP,OU=OPS",
                "name" : "disable"
            },
            {
                "dn" : "OU=employee,OU=KBP,OU=OPS",
                "name" : "employee"
            },
            {
                "dn" : "OU=organization mail,OU=KBP,OU=OPS",
                "name" : "organization mail"
            },
            {
                "dn" : "OU=unknown,OU=KBP,OU=OPS",
                "name" : "unknown"
            }
        ],
        [
            "_comment: Start point of LEGAL OU",
            {
                "dn" : "OU=LEGAL,OU=OPS",
                "name" : "LEGAL"
            },
            {
                "dn" : "OU=none,OU=LEGAL,OU=OPS",
                "name" : "none"
            }
        ],
        [
            "_comment: Start point of OPS-IN OU",
            {
                "dn" : "OU=OPS-IN,OU=OPS",
                "name" : "OPS-IN"
            }
        ],
        [
            "_comment: Start point of OPS-PM OU",
            {
                "dn" : "OU=OPS-PM,OU=OPS",
                "name" : "OPS-PM"
            },
            {
                "dn" : "OU=disable,OU=OPS-PM,OU=OPS",
                "name" : "disable"
            },
            {
                "dn" : "OU=Minister,OU=OPS-PM,OU=OPS",
                "name" : "Minister"
            }
        ],
        [
            "_comment: Start point of OPS-Reporter OU",
            {
                "dn" : "OU=OPS-Reporter,OU=OPS",
                "name" : "OPS-Reporter"
            }
        ],
        [
            "_comment: Start point of PCNI OU",
            {
                "dn" : "OU=PCNI,OU=OPS",
                "name" : "PCNI"
            },
            {
                "dn" : "OU=disable,OU=PCNI,OU=OPS",
                "name" : "disable"
            },
            {
                "dn" : "OU=employee,OU=PCNI,OU=OPS",
                "name" : "employee"
            },
            {
                "dn" : "OU=none,OU=PCNI,OU=OPS",
                "name" : "none"
            },
            {
                "dn" : "OU=organization mail,OU=PCNI,OU=OPS",
                "name" : "organization mail"
            }
        ],
        [
            "_comment: Start point of PERSD OU",
            {
                "dn" : "OU=PERSD,OU=OPS",
                "name" : "PERSD"
            },
            {
                "dn" : "OU=Admin,OU=PERSD,OU=OPS",
                "name" : "Admin"
            },
            {
                "dn" : "OU=Discipline,OU=PERSD,OU=OPS",
                "name" : "Discipline"
            },
            {
                "dn" : "OU=Manpower,OU=PERSD,OU=OPS",
                "name" : "Manpower"
            },
            {
                "dn" : "OU=none,OU=PERSD,OU=OPS",
                "name" : "none"
            },
            {
                "dn" : "OU=PersonnelDirector,OU=PERSD,OU=OPS",
                "name" : "PersonnelDirector"
            },
            {
                "dn" : "OU=Recruitment,OU=PERSD,OU=OPS",
                "name" : "Recruitment"
            }
        ],
        [
            "_comment: Start point of PSDG OU",
            {
                "dn" : "OU=PSDG,OU=OPS",
                "name" : "PSDG"
            },
            {
                "dn" : "OU=employee,OU=PSDG,OU=OPS",
                "name" : "employee"
            },
            {
                "dn" : "OU=none,OU=PSDG,OU=OPS",
                "name" : "none"
            }
        ],
        [
            "_comment: Start point of SAPD OU",
            {
                "dn" : "OU=SAPD,OU=OPS",
                "name" : "SAPD"
            },
            {
                "dn" : "OU=DIRECTOR,OU=SAPD,OU=OPS",
                "name" : "DIRECTOR"
            },
            {
                "dn" : "OU=disable,OU=SAPD,OU=OPS",
                "name" : "disable"
            },
            {
                "dn" : "OU=GA,OU=SAPD,OU=OPS",
                "name" : "GA"
            },
            {
                "dn" : "OU=ME,OU=SAPD,OU=OPS",
                "name" : "ME"
            },
            {
                "dn" : "OU=mocplan,OU=SAPD,OU=OPS",
                "name" : "mocplan"
            },
            {
                "dn" : "OU=none,OU=SAPD,OU=OPS",
                "name" : "none"
            },
            {
                "dn" : "OU=organization e-mail,OU=SAPD,OU=OPS",
                "name" : "organization e-mail"
            },
            {
                "dn" : "OU=SOGA,OU=SAPD,OU=OPS",
                "name" : "SOGA"
            },
            {
                "dn" : "OU=SP,OU=SAPD,OU=OPS",
                "name" : "SP"
            },
            {
                "dn" : "OU=test,OU=SAPD,OU=OPS",
                "name" : "test"
            },
            {
                "dn" : "OU=WP,OU=SAPD,OU=OPS",
                "name" : "WP"
            }
        ],
        [
            "_comment: Start point of Temp OU",
            {
                "dn" : "OU=Temp,OU=OPS",
                "name" : "Temp"
            }
        ],
        [
            "_comment: Start point of TESTNAC OU",
            {
                "dn" : "OU=TESTNAC,OU=OPS",
                "name" : "TESTNAC"
            }
        ],
        [
            "_comment: Start point of User Undefined OU",
            {
                "dn" : "OU=User Undefined,OU=OPS",
                "name" : "User Undefined"
            },
            {
                "dn" : "OU=disable,OU=User Undefined,OU=OPS",
                "name" : "disable"
            }
        ],
        [
            "_comment: Start point of Vendor OU",
            {
                "dn" : "OU=Vendor,OU=OPS",
                "name" : "Vendor"
            }
        ],
        [
            "_comment: Start point of VPN-Users OU",
            {
                "dn" : "OU=VPN-Users,OU=OPS",
                "name" : "VPN-Users"
            }
        ]
    ]
    
}